bdvr/__init__.py
bdvr-0.12.0.dist-info/entry_points.txt
bdvr-0.12.0.dist-info/LICENSE
bdvr-0.12.0.dist-info/WHEEL
bdvr-0.12.0.dist-info/METADATA
bdvr-0.12.0.dist-info/RECORD
