Metadata-Version: 2.1
Name: bdvr
Version: 0.12.0
Summary: customized report generated from set of blackduck reports that gives 'color coded vulnerabilities', and 'source paths' including 'direct' and 'indirect dependencies' details all in one report
License: MIT
Author: dineshr93gmail.com
Requires-Python: >=3.8,<4.0
Classifier: License :: OSI Approved :: MIT License
Classifier: Programming Language :: Python :: 3
Classifier: Programming Language :: Python :: 3.8
Classifier: Programming Language :: Python :: 3.9
Classifier: Programming Language :: Python :: 3.10
Requires-Dist: pandas (>=1.4.3,<2.0.0)
Requires-Dist: universal-startfile (>=0.1.3,<0.2.0)
